sms/__init__.py
sms/gap.py
sms_gap-0.1.0.dist-info/LICENSE
sms_gap-0.1.0.dist-info/METADATA
sms_gap-0.1.0.dist-info/WHEEL
sms_gap-0.1.0.dist-info/top_level.txt
sms_gap-0.1.0.dist-info/RECORD
